fiotclient/__init__.py
fiotclient/config.py
fiotclient/context.py
fiotclient/iot.py
fiotclient/utils.py
tests/__init__.py
tests/test_context.py
tests/test_iot.py
fiotclient-0.7.16.dist-info/LICENSE
fiotclient-0.7.16.dist-info/METADATA
fiotclient-0.7.16.dist-info/WHEEL
fiotclient-0.7.16.dist-info/top_level.txt
fiotclient-0.7.16.dist-info/RECORD
