Metadata-Version: 2.1
Name: fiotclient
Version: 0.7.16
Summary: Python client library for IoT and Context related API management on FIWARE platform
Home-page: https://github.com/FIoT-Client/fiot-client-ngsi-python
Author: Lucas Cristiano Calixto Dantas
Author-email: lucascristiano27@gmail.com
License: MIT
Keywords: fiware api iot things context development
Platform: UNKNOWN
Classifier: Development Status :: 4 - Beta
Classifier: Intended Audience :: Developers
Classifier: Topic :: Software Development :: Libraries
Classifier: License :: OSI Approved :: MIT License
Classifier: Programming Language :: Python :: 3.6
Classifier: Programming Language :: Python :: 3.7
Requires-Python: >=3.6, <4
Requires-Dist: requests
Requires-Dist: paho-mqtt
